atactools/__init__.py
atactools/peaks/__init__.py
atactools/peaks/intervals.py
atactools/peaks/normalize.py
scripts/__init__.py
scripts/annotateTSS.py
scripts/selectFWPeaks.py
atactools-0.0.2.dist-info/METADATA
atactools-0.0.2.dist-info/WHEEL
atactools-0.0.2.dist-info/entry_points.txt
atactools-0.0.2.dist-info/top_level.txt
atactools-0.0.2.dist-info/RECORD
